py_kabusapi/__init__.py
py_kabusapi/api.py
py_kabusapi/const.py
py_kabusapi/error.py
py_kabusapi/response_model.py
py_kabusapi-1.0.0.dist-info/licenses/LICENSE
tests/__init__.py
tests/test_api.py
tests/test_import.py
py_kabusapi-1.0.0.dist-info/METADATA
py_kabusapi-1.0.0.dist-info/WHEEL
py_kabusapi-1.0.0.dist-info/top_level.txt
py_kabusapi-1.0.0.dist-info/RECORD
