Metadata-Version: 2.4
Name: py-kabusapi
Version: 1.0.0
Summary: Python wrapper for kabuステーション API
Author: Sakaguchi Ryo
Author-email: Sakaguchi Ryo <sakaguchi@sk-techfirm.com>
Requires-Python: >=3.10
License-File: LICENSE
Requires-Dist: requests
Requires-Dist: ipython
Requires-Dist: ruff
Requires-Dist: pydantic
Requires-Dist: websocket-client
Requires-Dist: pytest
Dynamic: author
Dynamic: license-file
Dynamic: requires-python
